setup.py
text_display/__init__.py
text_display.egg-info/PKG-INFO
text_display.egg-info/SOURCES.txt
text_display.egg-info/dependency_links.txt
text_display.egg-info/requires.txt
text_display.egg-info/top_level.txt