Metadata-Version: 2.1
Name: text-display
Version: 0.1
Summary: Python package to display content of a text file
Author: Your Name
